pybingwallpaper/__init__.py
pybingwallpaper/bingwallpaper.py
pybingwallpaper/config.py
pybingwallpaper/log.py
pybingwallpaper/main.py
pybingwallpaper/py23.py
pybingwallpaper/record.py
pybingwallpaper/rev.py
pybingwallpaper/setter.py
pybingwallpaper/webutil.py
pybingwallpaper/winsetter.py
pybingwallpaper/ntlmauth/HTTPNtlmAuthHandler.py
pybingwallpaper/ntlmauth/U32.py
pybingwallpaper/ntlmauth/__init__.py
pybingwallpaper/ntlmauth/des.py
pybingwallpaper/ntlmauth/des_c.py
pybingwallpaper/ntlmauth/des_data.py
pybingwallpaper/ntlmauth/ntlm.py
PyBingWallpaper-1.5.6.dist-info/LICENSE-zhcn.txt
PyBingWallpaper-1.5.6.dist-info/LICENSE.md
PyBingWallpaper-1.5.6.dist-info/LICENSE.txt
PyBingWallpaper-1.5.6.dist-info/METADATA
PyBingWallpaper-1.5.6.dist-info/WHEEL
PyBingWallpaper-1.5.6.dist-info/entry_points.txt
PyBingWallpaper-1.5.6.dist-info/top_level.txt
PyBingWallpaper-1.5.6.dist-info/RECORD
